{"buildings":[{"flip":true,"type":"deco_sandbags_row","x":6,"y":40},{"flip":false,"type":"deco_dirtroad_cap_Down","x":-7,"y":39},{"flip":true,"type":"deco_frontier_streetSign","x":5,"y":51},{"flip":false,"type":"deco_dirtroad_straight","x":5,"y":8},{"flip":true,"type":"deco_crates","x":-7,"y":40},{"flip":true,"type":"deco_frontier_clothesline","x":27,"y":28},{"flip":false,"type":"deco_dirtroad_cap_Down","x":9,"y":47},{"flip":false,"type":"deco_sandbag","x":-11,"y":28},{"flip":false,"type":"deco_dirtroad_cap_Down","x":-19,"y":35},{"flip":false,"type":"deco_dirtroad_cap_Down","x":11,"y":47},{"flip":false,"type":"deco_dirtroad_cap_Down","x":15,"y":8},{"flip":false,"type":"deco_dirtroad_cap_Down","x":-7,"y":33},{"flip":false,"type":"deco_dirtroad_cap_Down","x":-7,"y":37},{"flip":true,"type":"deco_crates","x":4,"y":13},{"flip":false,"type":"deco_dirtroad_cap_Down","x":13,"y":8},{"flip":false,"type":"deco_damage1x1_00","x":3,"y":46},{"flip":false,"type":"deco_dirtroad_straight","x":1,"y":10},{"flip":false,"type":"deco_dirtroad_cap_Down","x":-1,"y":41},{"flip":true,"type":"deco_barrel_oil","x":9,"y":16},{"flip":false,"type":"deco_dirtroad_cap_Down","x":11,"y":14},{"flip":false,"type":"deco_crates","x":-4,"y":17},{"flip":true,"type":"deco_mountain_flat2","x":-12,"y":41},{"flip":false,"type":"deco_damage2x2_00","x":-3,"y":31},{"flip":false,"type":"deco_dirtroad_cap_Down","x":-3,"y":41},{"components":[{"_t":"Taxes","permanentlyOff":true}],"flip":false,"type":"comp_civHouse_camp","x":20,"y":19},{"flip":false,"type":"deco_damage2x2_00","x":-2,"y":25},{"flip":false,"type":"deco_dirtroad_straight","x":-1,"y":8},{"flip":false,"type":"deco_crates","x":23,"y":12},{"flip":true,"type":"deco_frontier_diner","x":13,"y":30},{"flip":false,"type":"deco_dirtroad_cap_Down","x":-7,"y":24},{"flip":false,"type":"deco_dirtroad_straight","x":3,"y":8},{"flip":false,"type":"deco_sandbag","x":7,"y":39},{"flip":true,"type":"deco_sandbags_row","x":-7,"y":38},{"flip":true,"type":"deco_dirtroad_cap_Down","x":11,"y":38},{"flip":false,"type":"deco_dirtroad_cap_Down","x":-1,"y":28},{"flip":false,"type":"deco_dirtroad_cap_Down","x":11,"y":28},{"flip":false,"type":"deco_dirtroad_cap_Down","x":-17,"y":35},{"flip":false,"type":"deco_dirtroad_cap_Down","x":-7,"y":30},{"flip":true,"type":"deco_mountain_flat2","x":-4,"y":36},{"flip":false,"type":"deco_dirtroad_cap_Down","x":3,"y":55},{"flip":false,"type":"deco_streetLamp","x":13,"y":43},{"flip":false,"type":"deco_dirtroad_cap_Down","x":1,"y":28},{"flip":false,"type":"deco_frontier_clothesline","x":20,"y":33},{"flip":true,"type":"deco_frontier_toolShed","x":0,"y":12},{"flip":true,"type":"deco_crater_02","x":10,"y":0},{"flip":false,"type":"deco_raider_drumfire","x":2,"y":17},{"flip":false,"type":"comp_defCombat_fortressArmored","x":-9,"y":15},{"flip":false,"type":"deco_dirtroad_cap_Down","x":7,"y":47},{"flip":true,"type":"comp_defCombat_fortressArmored","x":15,"y":44},{"components":[{"_t":"Taxes","permanentlyOff":true}],"flip":false,"type":"comp_civHouse_camp","x":-4,"y":11},{"flip":false,"type":"deco_dirtroad_cap_Down","x":11,"y":20},{"flip":false,"type":"deco_crates","x":19,"y":12},{"flip":false,"type":"deco_dirtroad_cap_Down","x":11,"y":24},{"flip":false,"type":"deco_mountain_flat1","x":-7,"y":43},{"flip":false,"type":"deco_crate_orange","x":22,"y":11},{"flip":false,"type":"comp_defCombat_raiderbombard_damaged","x":-3,"y":34},{"flip":false,"type":"deco_dirtroad_straight","x":3,"y":6},{"flip":false,"type":"deco_crates","x":23,"y":11},{"flip":false,"type":"deco_dirtroad_cap_Down","x":-7,"y":35},{"flip":false,"type":"deco_crater_03","x":3,"y":1},{"flip":false,"type":"deco_dirtroad_straight","x":9,"y":8},{"flip":true,"type":"deco_sandbags_corner1","x":-11,"y":28},{"flip":true,"type":"deco_frontier_cabin_humble","x":-6,"y":24},{"flip":true,"type":"deco_damaged_recon","x":1,"y":8},{"flip":true,"type":"deco_frontier_comfy_trailer","x":-5,"y":3},{"flip":false,"type":"deco_dirtroad_cap_Down","x":5,"y":47},{"flip":false,"type":"deco_raider_drumfire","x":10,"y":36},{"components":[{"_t":"Job","currentJob":{"jobId":"job_convenienceStore_20","percentDone":6}}],"flip":false,"type":"comp_civJob_minimart","x":2,"y":30},{"flip":false,"type":"deco_raider_drumfire","x":-1,"y":9},{"flip":false,"type":"deco_frontier_chairs","x":5,"y":46},{"flip":false,"type":"deco_frontier_clothesline","x":26,"y":20},{"flip":false,"type":"deco_frontier_clothesline","x":21,"y":33},{"flip":false,"type":"deco_dirtroad_cap_Down","x":-15,"y":35},{"flip":true,"type":"deco_frontier_clothesline","x":27,"y":27},{"flip":false,"type":"deco_dirtroad_cap_Down","x":3,"y":51},{"flip":false,"type":"deco_raider_junkpile","x":7,"y":17},{"flip":true,"type":"deco_crater_01","x":0,"y":34},{"flip":false,"type":"deco_dirtroad_cap_Down","x":-13,"y":35},{"flip":false,"type":"deco_crater_01","x":20,"y":25},{"components":[{"_t":"Taxes","permanentlyOff":true}],"flip":false,"type":"comp_civHouse_camp","x":-2,"y":21},{"flip":false,"type":"deco_sandbag","x":-11,"y":32},{"flip":true,"type":"deco_damaged_recon","x":3,"y":40},{"flip":false,"type":"deco_dirtroad_cap_Down","x":1,"y":16},{"flip":true,"type":"deco_frontier_grill","x":24,"y":26},{"flip":true,"type":"deco_bush_smallGreen","x":-3,"y":45},{"flip":false,"type":"deco_crates","x":1,"y":42},{"flip":false,"type":"deco_dirtroad_cap_Down","x":-7,"y":22},{"flip":false,"type":"deco_dirtroad_straight","x":7,"y":8},{"flip":false,"type":"deco_damage3x3_00","x":-1,"y":25},{"flip":false,"type":"deco_raider_drumfire","x":-7,"y":37},{"flip":false,"type":"deco_dirtroad_cap_Down","x":11,"y":40},{"flip":false,"type":"deco_dirtroad_cap_Down","x":-5,"y":28},{"flip":false,"type":"comp_res_warehouse_medium","x":13,"y":10},{"flip":false,"type":"deco_dirtroad_cap_Down","x":3,"y":59},{"flip":false,"type":"deco_frontier_comfy_trailer","x":8,"y":10},{"flip":true,"type":"deco_raider_junkpile","x":0,"y":31},{"flip":true,"type":"deco_frontier_clothesline","x":24,"y":15},{"flip":false,"type":"deco_dirtroad_cap_Down","x":11,"y":10},{"flip":false,"type":"deco_crater_02","x":6,"y":50},{"flip":false,"type":"deco_frontier_hotel","x":4,"y":24},{"flip":false,"type":"deco_sandbags_row","x":-11,"y":30},{"flip":false,"type":"deco_dirtroad_straight","x":3,"y":10},{"flip":true,"type":"deco_crates","x":20,"y":12},{"flip":false,"type":"deco_dirtroad_straight","x":1,"y":6},{"components":[{"_t":"Taxes","permanentlyOff":true}],"flip":false,"type":"comp_civHouse_camp","x":18,"y":29},{"flip":false,"type":"deco_tree_lightOak","x":-3,"y":-2},{"flip":false,"type":"deco_dirtroad_cap_Down","x":11,"y":32},{"flip":false,"type":"deco_dirtroad_cap_Down","x":3,"y":20},{"flip":true,"type":"deco_sandbag","x":2,"y":43},{"flip":false,"type":"deco_crates","x":21,"y":10},{"flip":false,"type":"comp_deco_guard_post","x":-9,"y":29},{"flip":false,"type":"deco_damage2x2_00","x":-7,"y":39},{"flip":false,"type":"deco_dirtroad_cap_Down","x":9,"y":28},{"flip":false,"type":"deco_dirtroad_cap_Down","x":5,"y":16},{"flip":true,"type":"deco_crate_red","x":15,"y":49},{"flip":false,"type":"deco_frontier_homey_trailer","x":15,"y":17},{"flip":false,"type":"deco_dirtroad_cap_Down","x":11,"y":45},{"flip":false,"type":"deco_dirtroad_cap_Down","x":9,"y":18},{"flip":false,"type":"deco_watertower","x":13,"y":27},{"flip":false,"type":"deco_sandbags_corner2","x":-11,"y":32},{"flip":false,"type":"deco_sandbag","x":5,"y":39},{"flip":true,"type":"deco_crater_01","x":14,"y":51},{"flip":false,"type":"deco_crates","x":-4,"y":15},{"flip":true,"type":"deco_frontier_clothesline","x":27,"y":29},{"flip":true,"type":"deco_frontier_clothesline","x":24,"y":14},{"flip":false,"type":"deco_crate_toxic","x":1,"y":46},{"flip":false,"type":"deco_dirtroad_cap_Down","x":11,"y":30},{"flip":false,"type":"deco_dirtroad_cap_Down","x":11,"y":16},{"flip":false,"type":"deco_dirtroad_cap_Down","x":-5,"y":41},{"flip":true,"type":"deco_tree_willow","x":22,"y":17},{"flip":true,"type":"comp_defCombat_fortressArmored","x":21,"y":5},{"flip":true,"type":"deco_dirtroad_cap_Down","x":3,"y":53},{"flip":false,"type":"deco_dirtroad_cap_Down","x":-7,"y":31},{"flip":false,"type":"deco_crates","x":21,"y":12},{"flip":false,"type":"deco_dirtroad_cap_Down","x":11,"y":26},{"components":[{"_t":"Taxes","permanentlyOff":true}],"flip":false,"type":"comp_civHouse_shelter","x":22,"y":28},{"flip":true,"type":"deco_crates","x":19,"y":10},{"flip":false,"type":"deco_dirtroad_cap_Down","x":3,"y":45},{"flip":false,"type":"deco_frontier_mailbox","x":5,"y":49},{"flip":false,"type":"deco_bush_medium","x":8,"y":45},{"flip":true,"type":"deco_damage3x3_00","x":13,"y":34},{"flip":false,"type":"deco_crate_red","x":-6,"y":14},{"flip":false,"type":"deco_sandbag","x":9,"y":37},{"flip":true,"type":"deco_sandbags_row","x":8,"y":40},{"flip":false,"type":"deco_mountain_flat2","x":-12,"y":37},{"flip":true,"type":"deco_crates","x":16,"y":48},{"flip":false,"type":"deco_dirtroad_cap_Down","x":3,"y":57},{"flip":false,"type":"deco_crates","x":15,"y":47},{"flip":false,"type":"deco_dirtroad_cap_Down","x":-7,"y":41},{"flip":false,"type":"deco_bush_smallGreen","x":-5,"y":39},{"flip":false,"type":"deco_raider_drumfire","x":2,"y":6},{"flip":false,"type":"deco_dirtroad_cap_Down","x":3,"y":43},{"flip":false,"type":"deco_crate_orange","x":4,"y":44},{"flip":false,"type":"deco_crates","x":-9,"y":18},{"flip":false,"type":"deco_dirtroad_straight","x":-1,"y":10},{"flip":false,"type":"deco_frontier_clothesline","x":22,"y":33},{"flip":false,"type":"deco_dirtroad_cap_Down","x":3,"y":41},{"flip":false,"type":"deco_dirtroad_cap_Down","x":1,"y":20},{"flip":false,"type":"deco_dirtroad_cap_Down","x":11,"y":36},{"components":[{"_t":"Taxes","permanentlyOff":true}],"flip":true,"type":"comp_civHouse_shelter","x":24,"y":23},{"flip":true,"type":"deco_crater_01","x":2,"y":24},{"flip":false,"type":"deco_dirtroad_cap_Down","x":-9,"y":35},{"flip":false,"type":"deco_damage2x2_00","x":3,"y":42},{"flip":false,"type":"deco_dirtroad_cap_Down","x":3,"y":16},{"flip":true,"type":"deco_bush_medium","x":15,"y":35},{"flip":true,"type":"deco_crates","x":22,"y":9},{"flip":false,"type":"deco_crate_red","x":21,"y":9},{"flip":false,"type":"deco_raider_drumfire","x":6,"y":39},{"flip":false,"type":"deco_dirtroad_cap_Down","x":-11,"y":35},{"flip":false,"type":"deco_dirtroad_cap_Down","x":-21,"y":35},{"flip":false,"type":"deco_crates","x":20,"y":46},{"flip":true,"type":"deco_damage3x3_00","x":13,"y":53},{"flip":false,"type":"deco_dirtroad_cap_Down","x":-7,"y":28},{"flip":false,"type":"deco_crates","x":15,"y":48},{"flip":false,"type":"deco_dirtroad_cap_Down","x":17,"y":6},{"flip":false,"type":"deco_mountain_flat2","x":1,"y":36},{"flip":false,"type":"deco_crates","x":4,"y":12},{"flip":false,"type":"deco_dirtroad_cap_Down","x":11,"y":8},{"flip":false,"type":"deco_mountain_flat2","x":-8,"y":44},{"flip":false,"type":"deco_dirtroad_cap_Down","x":11,"y":12},{"flip":true,"type":"deco_crates","x":-5,"y":15},{"flip":true,"type":"deco_raider_junkpile","x":-5,"y":37},{"flip":false,"type":"deco_crates","x":21,"y":14},{"flip":false,"type":"deco_dirtroad_straight","x":5,"y":10},{"flip":false,"type":"deco_damage2x2_00","x":15,"y":6},{"flip":false,"type":"deco_dirtroad_straight","x":-1,"y":6},{"flip":false,"type":"deco_dirtroad_cap_Down","x":1,"y":18},{"flip":false,"type":"deco_dirtroad_straight","x":1,"y":8},{"components":[{"_t":"Taxes","permanentlyOff":true}],"flip":false,"type":"comp_civHouse_camp","x":15,"y":23},{"flip":false,"type":"deco_dirtroad_cap_Down","x":5,"y":20},{"flip":false,"type":"deco_bush_medium","x":10,"y":14},{"flip":false,"type":"deco_dirtroad_cap_Down","x":-7,"y":20},{"flip":false,"type":"deco_dirtroad_cap_Down","x":3,"y":47},{"flip":false,"type":"deco_dirtroad_cap_Down","x":7,"y":18},{"flip":false,"type":"deco_barrel_toxic","x":1,"y":44},{"flip":false,"type":"deco_dirtroad_cap_Down","x":5,"y":18},{"flip":true,"type":"map_terrain_bridgeFrontier","x":11,"y":40},{"flip":false,"type":"deco_raider_drumfire","x":2,"y":41},{"flip":false,"type":"deco_sandbag","x":9,"y":39},{"flip":true,"type":"deco_sandbags_row","x":3,"y":47},{"flip":false,"type":"deco_raider_junkpile","x":4,"y":46},{"components":[{"_t":"Job","currentJob":{"jobId":"job_homeDefense_20","percentDone":0}}],"flip":false,"type":"comp_civJob_gunshow","x":3,"y":18},{"flip":false,"type":"deco_dirtroad_cap_Down","x":17,"y":8},{"flip":false,"type":"deco_crates","x":13,"y":44},{"flip":false,"type":"deco_dirtroad_cap_Down","x":11,"y":43},{"flip":true,"type":"deco_crates","x":-9,"y":20},{"flip":false,"type":"deco_crater_02","x":-20,"y":21},{"flip":false,"type":"deco_raider_drumfire","x":5,"y":20},{"flip":false,"type":"deco_barrel_oil","x":13,"y":25},{"flip":false,"type":"deco_sandbag","x":-11,"y":30},{"flip":false,"type":"comp_deco_guard_post","x":13,"y":38},{"flip":false,"type":"deco_dirtroad_cap_Down","x":11,"y":18},{"flip":false,"type":"deco_sandbag","x":-9,"y":32},{"flip":false,"type":"deco_dirtroad_cap_Down","x":11,"y":22},{"components":[{"_t":"Taxes","permanentlyOff":true}],"flip":true,"type":"comp_civHouse_camp","x":8,"y":4},{"flip":false,"type":"deco_dirtroad_cap_Down","x":7,"y":28},{"flip":false,"type":"deco_crater_01","x":0,"y":48},{"flip":false,"type":"deco_dirtroad_cap_Down","x":3,"y":49},{"flip":false,"type":"deco_dirtroad_straight","x":5,"y":6},{"flip":false,"type":"deco_bush_smallGreen","x":-9,"y":41},{"flip":true,"type":"deco_sandbags_row","x":5,"y":47},{"flip":false,"type":"deco_dirtroad_cap_Down","x":3,"y":18},{"flip":false,"type":"deco_dirtroad_cap_Down","x":5,"y":28},{"flip":false,"type":"deco_dirtroad_cap_Down","x":-7,"y":26},{"flip":false,"type":"deco_tree_fallMapleOrange","x":8,"y":20},{"flip":false,"type":"deco_damage4x4_00","x":-4,"y":33},{"flip":true,"type":"deco_mountain_flat1","x":-4,"y":43},{"flip":true,"type":"deco_damage3x3_00","x":15,"y":3},{"flip":false,"type":"deco_bush_smallGreen","x":1,"y":37},{"flip":true,"type":"deco_sandbags_row","x":-9,"y":33},{"flip":false,"type":"deco_crates","x":2,"y":12},{"flip":false,"type":"deco_raider_drumfire","x":6,"y":11},{"flip":false,"type":"deco_dirtroad_cap_Down","x":11,"y":34},{"flip":false,"type":"deco_dirtroad_cap_Down","x":-3,"y":28},{"flip":false,"type":"deco_crates","x":-8,"y":20},{"flip":false,"type":"deco_sandbag","x":-10,"y":28},{"flip":false,"type":"deco_sandbag","x":3,"y":44},{"flip":false,"type":"deco_crater_01","x":-13,"y":32},{"components":[{"_t":"Taxes","permanentlyOff":true}],"flip":true,"type":"comp_civHouse_camp","x":7,"y":31},{"flip":true,"type":"deco_tree_smallOrange","x":4,"y":14},{"flip":true,"type":"deco_damage2x2_00","x":-8,"y":38},{"flip":false,"type":"deco_dirtroad_cap_Down","x":3,"y":28},{"flip":false,"type":"deco_dirtroad_cap_Down","x":1,"y":41},{"flip":false,"type":"deco_raider_drumfire","x":5,"y":43},{"flip":false,"type":"deco_dirtroad_cap_Down","x":-7,"y":31}],"initialExpansions":[[4,4],[3,4],[2,4],[1,4],[0,4],[-1,4],[-2,4],[-3,4],[-4,4],[-5,4],[4,3],[3,3],[2,3],[1,3],[0,3],[-1,3],[-2,3],[-3,3],[-4,3],[-5,3],[4,2],[3,2],[2,2],[1,2],[0,2],[-1,2],[-2,2],[-3,2],[-4,2],[-5,2],[4,1],[3,1],[2,1],[1,1],[0,1],[-1,1],[-2,1],[-3,1],[-4,1],[-5,1],[4,0],[3,0],[2,0],[1,0],[0,0],[-1,0],[-2,0],[-3,0],[-4,0],[-5,0],[4,-1],[3,-1],[2,-1],[1,-1],[0,-1],[-1,-1],[-2,-1],[-3,-1],[-4,-1],[-5,-1],[4,-2],[3,-2],[2,-2],[1,-2],[0,-2],[-1,-2],[-2,-2],[-3,-2],[-4,-2],[-5,-2],[4,-3],[3,-3],[2,-3],[1,-3],[0,-3],[-1,-3],[-2,-3],[-3,-3],[-4,-3],[-5,-3],[4,-4],[3,-4],[2,-4],[1,-4],[0,-4],[-1,-4],[-2,-4],[-3,-4],[-4,-4],[-5,-4],[4,-5],[3,-5],[2,-5],[1,-5],[0,-5],[-1,-5],[-2,-5],[-3,-5],[-4,-5],[-5,-5]],"militias":["sw_guy_assaultrifle","sw_guy_assaultrifle","sw_guy_grenade","sw_guy_machete","sw_guy_rpg","sw_guy_shield","sw_guy_shield","sw_guy_uzi","sw_veh_artillery","sw_veh_truck_rocket"],"name":"map_SilverWolvesDepot","startingCameraLocation":{"x":5,"y":38},"startingCameraScale":1.28,"tileLayoutFile":"terrain_SilverWolvesDepot.json","tileSet":"WorldMapTiles.pvr"}